[
  { "Id": 1, "Name": "Alice",   "City": "Paris",    "Age": 30, "Job": "Engineer" },
  { "Id": 2, "Name": "Bob",     "City": "Lyon",     "Age": 25, "Job": "Designer" },
  { "Id": 3, "Name": "Charlie", "City": "Paris",    "Age": 35, "Job": "Manager"  },
  { "Id": 4, "Name": "Diana",   "City": "Bordeaux", "Age": 28, "Job": "Engineer" },
  { "Id": 5, "Name": "Eve",     "City": "Paris",    "Age": 22, "Job": "Intern"   },
  { "Id": 6, "Name": "Frank",   "City": "Lyon",     "Age": 40, "Job": "Manager"  },
  { "Id": 7, "Name": "Grace",   "City": "Bordeaux", "Age": 31, "Job": "Designer" },
  { "Id": 8, "Name": "Hank",    "City": "Paris",    "Age": 27, "Job": "Engineer" }
]
